AISTLAB_novel_grab-1.2.12.dist-info/DESCRIPTION.rst
AISTLAB_novel_grab-1.2.12.dist-info/METADATA
AISTLAB_novel_grab-1.2.12.dist-info/RECORD
AISTLAB_novel_grab-1.2.12.dist-info/WHEEL
AISTLAB_novel_grab-1.2.12.dist-info/entry_points.txt
AISTLAB_novel_grab-1.2.12.dist-info/metadata.json
AISTLAB_novel_grab-1.2.12.dist-info/top_level.txt
novel_grab/__init__.py
novel_grab/grab_config.json
novel_grab/novel_grab.py
novel_grab/test.py
