Metadata-Version: 2.0
Name: AISTLAB-novel-grab
Version: 1.2.12
Summary: novel grab crawler module using python3 and lxml
Home-page: https://github.com/winxos/novel_grab
Author: winxos
Author-email: winxos@hotmail.com
License: MIT License
Keywords: crawler,winxos,AISTLAB
Platform: UNKNOWN
Classifier: Development Status :: 3 - Alpha
Classifier: Topic :: Utilities
Classifier: Programming Language :: Python :: 3
Classifier: Programming Language :: Python :: 3.2
Classifier: Programming Language :: Python :: 3.3
Classifier: Programming Language :: Python :: 3.4
Classifier: Programming Language :: Python :: 3.5
Classifier: Programming Language :: Python :: 3.6
Requires-Dist: lxml
